{
  "name" : "wfTransitionValidForm",
  "title" : "DMN редактор",
  "type" : "Form",
  "bc" : "wfTransitionValid",
  "showCondition" : {
    "key" : "wfTransitionValid",
    "sequence" : 1,
    "params" : {
      "fieldKey" : "validCd",
      "value" : "DMN"
    }
  },
  "fields" : [ {
    "blockId" : "1",
    "name" : "",
    "fullSize" : true,
    "fields" : [ {
      "title" : "",
      "key" : "dmn",
      "type" : "DMN",
      "popups" : {
        "fields" : {
          "popupBcName" : "wfTransitionValidDmnFields",
          "pickMap" : {
            "title" : "title",
            "key" : "key",
            "type" : "type",
            "values" : "values"
          }
        },
        "constants" : {
          "popupBcName" : "wfTransitionValidDmnConstants",
          "pickMap" : {
            "title" : "title",
            "key" : "key",
            "type" : "type"
          }
        }
      }
    } ]
  } ],
  "axisFields" : [ ],
  "chart" : [ ]
}