{
  "name" : "docGraph",
  "title" : "Графы",
  "template" : "DashboardView",
  "url" : "/screen/doc/view/docGraph",
  "widgets" : [ {
    "widgetName" : "bcExampleHeaderWidget10",
    "position" : 0,
    "gridWidth" : 2
  }, {
    "widgetName" : "bcExampleForm9",
    "position" : 1,
    "gridWidth" : 2,
    "descriptionFile" : "db/migration/liquibase/data/latest/screens/doc/views/descriptions/docGraph-bcExampleForm9.description.txt"
  }, {
    "widgetName" : "sqlDocGraphList2",
    "position" : 2,
    "gridWidth" : 2,
    "snippetFile" : "db/migration/liquibase/data/latest/screens/doc/views/snippets/docGraph-  null.snippet.txt"
  }, {
    "widgetName" : "sqlDocGraphList1",
    "position" : 2,
    "gridWidth" : 2,
    "snippetFile" : "db/migration/liquibase/data/latest/screens/doc/views/snippets/docGraph-  null.snippet.txt"
  } ]
}